{
  "name": "Client",
  "plural": "clients",
  "base": "User",
  "idInjection": true,
  "options": {
    "validateUpsert": true
  },
  "properties": {
    "name": {
      "type": "string",
      "required": true
    }
  },
  "validations": [],
  "relations": {
    "projects": {
      "type": "hasMany",
      "model": "Project",
      "foreignKey": "",
      "options": {
        "nestRemoting": true
      }
    }
  },
  "acls": [
    {
      "accessType": "*",
      "principalType": "ROLE",
      "principalId": "$everyone",
      "permission": "DENY"
    },
    {
      "accessType": "EXECUTE",
      "principalType": "ROLE",
      "principalId": "$owner",
      "permission": "ALLOW",
      "property": "__get__projects"
    },
    {
      "accessType": "EXECUTE",
      "principalType": "ROLE",
      "principalId": "$owner",
      "permission": "ALLOW",
      "property": "__create__projects"
    },
    {
      "accessType": "EXECUTE",
      "principalType": "ROLE",
      "principalId": "$owner",
      "permission": "ALLOW",
      "property": "__delete__projects"
    }
  ],
  "methods": {}
}
