{
  "name": "ComponentStack",
  "base": "PersistedModel",
  "idInjection": true,
  "options": {
    "validateUpsert": true
  },
  "properties": {
    "hours": {
      "type": "number",
      "required": true,
      "default": 0
    },
    "perc_of_total": {
      "type": "number",
      "required": false,
      "default": 0
    },
    "stackId": {
      "type": "string",
      "required": true
    }
  },
  "validations": [],
  "relations": {
    "stack": {
      "type": "belongsTo",
      "model": "Stack",
      "foreignKey": "",
      "options": {
        "nestRemoting": true
      }
    }
  },
  "acls": [],
  "methods": {}
}
